easy_bot/__init__.py
easy_bot/easy_bot.py
easy_bot/endpoints/ai_cores.py
easy_bot/endpoints/nim.py
easy_bot/endpoints/openaicore.py
easy_bot/errors/easy_bot.py
easy_bot/tools/tools.py
easy_bot/types/easy_bot_types.py
easy_bot/types/nim_types.py
easy_bot/utils/__init__.py
easy_bot/utils/code_interpreter.py
tests/__init__.py
tests/test_code_interpreter.py
tests/test_easy_bot.py
tests/test_nim.py
tests/test_openai.py
tests/test_tools.py
easybot_py-0.0.7.dist-info/LICENSE
easybot_py-0.0.7.dist-info/METADATA
easybot_py-0.0.7.dist-info/WHEEL
easybot_py-0.0.7.dist-info/top_level.txt
easybot_py-0.0.7.dist-info/RECORD
