Metadata-Version: 2.1
Name: easybot_py
Version: 0.0.7
Summary: A library to help and facilitate the creation of bots and AI assistants
Home-page: https://github.com/nervesscat/easy_bot
Author: Enrique Madrid
Author-email: contact@nervess.cat
Classifier: Programming Language :: Python :: 3
Classifier: License :: OSI Approved :: MIT License
Classifier: Operating System :: OS Independent
Requires-Python: >=3.12
License-File: LICENSE
Requires-Dist: openai
